LICENSE.txt
MANIFEST.in
README.rst
pyproject.toml
setup.py
tutor_webui.egg-info/PKG-INFO
tutor_webui.egg-info/SOURCES.txt
tutor_webui.egg-info/dependency_links.txt
tutor_webui.egg-info/entry_points.txt
tutor_webui.egg-info/requires.txt
tutor_webui.egg-info/top_level.txt
tutorwebui/__about__.py
tutorwebui/__init__.py
tutorwebui/cli.py
tutorwebui/plugin.py