Metadata-Version: 2.1
Name: tutor-webui
Version: 17.0.1
Summary: Web-based user interface plugin for Tutor
Home-page: https://overhang.io/overhangio/tutor-webui
Author: Overhang.IO
Author-email: contact@overhang.io
Maintainer: Edly
Maintainer-email: hina.khadim@arbisoft.com
License: AGPLv3
Project-URL: Documentation, https://docs.tutor.edly.io/
Project-URL: Code, https://github.com/overhangio/tutor-webui
Project-URL: Issue tracker, https://github.com/overhangio/tutor-webui/issues
Project-URL: Community, https://discuss.openedx.org
Classifier: Development Status :: 5 - Production/Stable
Classifier: Intended Audience :: Developers
Classifier: License :: OSI Approved :: GNU Affero General Public License v3
Classifier: Operating System :: OS Independent
Classifier: Programming Language :: Python
Classifier: Programming Language :: Python :: 3.8
Classifier: Programming Language :: Python :: 3.9
Classifier: Programming Language :: Python :: 3.10
Classifier: Programming Language :: Python :: 3.11
Classifier: Programming Language :: Python :: 3.12
Requires-Python: >=3.8
License-File: LICENSE.txt
Requires-Dist: tutor<18.0.0,>=17.0.0
Requires-Dist: click_repl>=0.3.0
Provides-Extra: dev
Requires-Dist: tutor[dev]<18.0.0,>=17.0.0; extra == "dev"
